cogames/__init__.py
cogames/auth.py
cogames/curricula.py
cogames/device.py
cogames/evaluate.py
cogames/game.py
cogames/main.py
cogames/play.py
cogames/py.typed
cogames/train.py
cogames/verbose.py
cogames/cli/base.py
cogames/cli/client.py
cogames/cli/leaderboard.py
cogames/cli/login.py
cogames/cli/mission.py
cogames/cli/policy.py
cogames/cli/submit.py
cogames/cli/utils.py
cogames/cogs_vs_clips/__init__.py
cogames/cogs_vs_clips/cogs_vs_clips_mapgen.md
cogames/cogs_vs_clips/mission.py
cogames/cogs_vs_clips/mission_utils.py
cogames/cogs_vs_clips/missions.py
cogames/cogs_vs_clips/procedural.py
cogames/cogs_vs_clips/sites.py
cogames/cogs_vs_clips/stations.py
cogames/cogs_vs_clips/tutorial_missions.py
cogames/cogs_vs_clips/variants.py
cogames/cogs_vs_clips/evals/README.md
cogames/cogs_vs_clips/evals/diagnostic_evals.py
cogames/cogs_vs_clips/evals/difficulty_variants.py
cogames/cogs_vs_clips/evals/integrated_evals.py
cogames/cogs_vs_clips/evals/spanning_evals.py
cogames/maps/canidate1_1000.map
cogames/maps/canidate1_1000_stations.map
cogames/maps/canidate1_500.map
cogames/maps/canidate1_500_stations.map
cogames/maps/canidate2_1000.map
cogames/maps/canidate2_1000_stations.map
cogames/maps/canidate2_500.map
cogames/maps/canidate2_500_stations.map
cogames/maps/canidate3_1000.map
cogames/maps/canidate3_1000_stations.map
cogames/maps/canidate3_500.map
cogames/maps/canidate3_500_stations.map
cogames/maps/canidate4_500.map
cogames/maps/canidate4_500_stations.map
cogames/maps/cave_base_50.map
cogames/maps/machina_100_stations.map
cogames/maps/machina_200_stations.map
cogames/maps/machina_200_stations_small.map
cogames/maps/machina_eval_exp01.map
cogames/maps/machina_eval_template_large.map
cogames/maps/machinatrainer4agents.map
cogames/maps/machinatrainer4agentsbase.map
cogames/maps/machinatrainerbig.map
cogames/maps/machinatrainersmall.map
cogames/maps/training_facility_clipped.map
cogames/maps/training_facility_open_1.map
cogames/maps/training_facility_open_2.map
cogames-0.3.49.dist-info/METADATA
cogames-0.3.49.dist-info/WHEEL
cogames-0.3.49.dist-info/entry_points.txt
cogames-0.3.49.dist-info/top_level.txt
cogames-0.3.49.dist-info/RECORD
