Metadata-Version: 2.4
Name: cogames
Version: 0.3.49
Summary: Multi-agent cooperative games
Requires-Python: <3.13,>=3.12
Requires-Dist: heavyball>=2.0.0
Requires-Dist: mettagrid==0.2.0.58
Requires-Dist: packaging>=24.0.0
Requires-Dist: pufferlib-core
Requires-Dist: pydantic>=2.11.5
Requires-Dist: pyyaml>=6.0.2
Requires-Dist: einops>=0.8.0
Requires-Dist: scipy>=1.15.3
Requires-Dist: typer>=0.19.2
Requires-Dist: rich>=13.7.0
Requires-Dist: fastapi>=0.115.0
Requires-Dist: uvicorn>=0.34.0
Requires-Dist: httpx>=0.28.1
